affiliate/.DS_Store
affiliate/__init__.py
affiliate/__init__.pyc
affiliate/admin.py
affiliate/admin.pyc
affiliate/app_settings.py
affiliate/app_settings.pyc
affiliate/forms.py
affiliate/forms.pyc
affiliate/middleware.py
affiliate/middleware.pyc
affiliate/models.py
affiliate/models.pyc
affiliate/utils.py
affiliate/utils.pyc
affiliate/views.py
affiliate/views.pyc
affiliate/locale/ru/LC_MESSAGES/django.mo
affiliate/locale/ru/LC_MESSAGES/django.po
affiliate/templatetags/.DS_Store
affiliate/templatetags/__init__.py
affiliate/templatetags/__init__.pyc
affiliate/templatetags/affiliate_tags.py
affiliate/templatetags/affiliate_tags.pyc
django_affiliate-0.4.0.dist-info/DESCRIPTION.rst
django_affiliate-0.4.0.dist-info/METADATA
django_affiliate-0.4.0.dist-info/RECORD
django_affiliate-0.4.0.dist-info/WHEEL
django_affiliate-0.4.0.dist-info/metadata.json
django_affiliate-0.4.0.dist-info/top_level.txt
tests/__init__.py
tests/test_affiliate_middleware.py
tests/test_affiliate_models.py
tests/test_affiliate_views.py
tests/utils.py
