Metadata-Version: 2.0
Name: django-affiliate
Version: 0.4.0
Summary: Affiliate system for django
Home-page: https://github.com/st4lk/django-affiliate
Author: st4lk
Author-email: alexevseev@gmail.com
License: BSD License
Keywords: django,affiliate,urls,track
Platform: Any
Classifier: Environment :: Web Environment
Classifier: Framework :: Django
Classifier: Intended Audience :: Developers
Classifier: License :: OSI Approved :: BSD License
Classifier: Operating System :: OS Independent
Classifier: Programming Language :: Python
Classifier: Topic :: Utilities
Requires-Dist: django (>=1.6,<1.9)
